{"nodes": [{"id": "divi5_brand_profile_skill", "label": "divi5-brand-profile Skill", "file_type": "document", "source_file": "skills/divi5-brand-profile/SKILL.md", "source_location": null, "source_url": null, "captured_at": null, "author": null, "contributor": null}, {"id": "divi5_brand_profile_schema", "label": "Brand Profile Canonical Schema", "file_type": "concept", "source_file": "skills/divi5-brand-profile/SKILL.md", "source_location": null, "source_url": null, "captured_at": null, "author": null, "contributor": null}, {"id": "divi5_brand_profile_sticky_fields", "label": "Sticky Fields (re-extraction)", "file_type": "rationale", "source_file": "skills/divi5-brand-profile/SKILL.md", "source_location": null, "source_url": null, "captured_at": null, "author": null, "contributor": null}], "edges": [{"source": "divi5_brand_profile_skill", "target": "divi5_brand_profile_schema", "relation": "references", "confidence": "EXTRACTED", "confidence_score": 1.0, "source_file": "skills/divi5-brand-profile/SKILL.md", "source_location": null, "weight": 1.0}, {"source": "divi5_brand_profile_skill", "target": "divi5_brand_profile_sticky_fields", "relation": "references", "confidence": "EXTRACTED", "confidence_score": 1.0, "source_file": "skills/divi5-brand-profile/SKILL.md", "source_location": null, "weight": 1.0}, {"source": "divi5_brand_profile_skill", "target": "divi5_extract_style_skill", "relation": "references", "confidence": "EXTRACTED", "confidence_score": 1.0, "source_file": "skills/divi5-brand-profile/SKILL.md", "source_location": null, "weight": 1.0}, {"source": "divi5_brand_profile_skill", "target": "divi5_extract_style_extract_from_export", "relation": "references", "confidence": "EXTRACTED", "confidence_score": 1.0, "source_file": "skills/divi5-brand-profile/SKILL.md", "source_location": null, "weight": 1.0}, {"source": "divi5_brand_profile_skill", "target": "divi5_page_generator_design_project_mode", "relation": "references", "confidence": "EXTRACTED", "confidence_score": 1.0, "source_file": "skills/divi5-brand-profile/SKILL.md", "source_location": null, "weight": 1.0}, {"source": "divi5_brand_profile_schema", "target": "plans_chat_driven_brand_profile_entity", "relation": "shares_data_with", "confidence": "INFERRED", "confidence_score": 0.95, "source_file": "skills/divi5-brand-profile/SKILL.md", "source_location": null, "weight": 1.0}], "hyperedges": []}